fyrd/__init__.py
fyrd/__main__.py
fyrd/basic.py
fyrd/conf.py
fyrd/helpers.py
fyrd/job.py
fyrd/local.py
fyrd/logme.py
fyrd/options.py
fyrd/queue.py
fyrd/run.py
fyrd/script_runners.py
fyrd/submission_scripts.py
fyrd-0.6.1b9.data/scripts/clean-job-files
fyrd-0.6.1b9.data/scripts/cluster-keywords
fyrd-0.6.1b9.data/scripts/monitor-jobs
fyrd-0.6.1b9.data/scripts/my-queue
fyrd-0.6.1b9.data/scripts/myq
fyrd-0.6.1b9.dist-info/DESCRIPTION.rst
fyrd-0.6.1b9.dist-info/METADATA
fyrd-0.6.1b9.dist-info/RECORD
fyrd-0.6.1b9.dist-info/WHEEL
fyrd-0.6.1b9.dist-info/entry_points.txt
fyrd-0.6.1b9.dist-info/metadata.json
fyrd-0.6.1b9.dist-info/top_level.txt
