Metadata-Version: 2.0
Name: fyrd
Version: 0.6.1b9
Summary: Submit functions and shell scripts to torque, slurm, or local machines
Home-page: https://fyrd.science
Author: Michael Dacre
Author-email: mike.dacre@gmail.com
License: MIT
Download-URL: https://github.com/MikeDacre/fyrd/v0.6.1b9.tar.gz
Keywords: slurm torque multiprocessing cluster job_management
Platform: UNKNOWN
Classifier: Development Status :: 4 - Beta
Classifier: Intended Audience :: Science/Research
Classifier: Environment :: Console
Classifier: Operating System :: POSIX :: Linux
Classifier: Natural Language :: English
Classifier: Topic :: System :: Clustering
Classifier: Topic :: System :: Monitoring
Classifier: Topic :: Software Development :: Libraries
Classifier: Topic :: Software Development :: Libraries :: Python Modules
Classifier: License :: OSI Approved :: MIT License
Classifier: Programming Language :: Python :: 2
Classifier: Programming Language :: Python :: 2.7
Classifier: Programming Language :: Python :: 3
Classifier: Programming Language :: Python :: 3.3
Classifier: Programming Language :: Python :: 3.4
Classifier: Programming Language :: Python :: 3.5
Classifier: Programming Language :: Python :: 3.6
Requires: dill
Requires: tabulate
Requires: six
Requires: tblib
Requires-Dist: dill
Requires-Dist: six
Requires-Dist: tabulate
Requires-Dist: tblib
